{
  "@context": "https://schema.org",
  "@type": "Product",
  "name": "Wireless Headphones WH-1000",
  "description": "Premium over-ear headphones with active noise cancellation, 40-hour battery life, and superior sound quality. Perfect for music lovers and professionals.",
  "image": [
    "https://example.com/images/wh-1000-front.jpg",
    "https://example.com/images/wh-1000-side.jpg",
    "https://example.com/images/wh-1000-case.jpg"
  ],
  "sku": "WH-1000",
  "mpn": "WH-1000-BLK",
  "gtin13": "1234567890123",
  "brand": {
    "@type": "Brand",
    "name": "AudioTech"
  },
  "manufacturer": {
    "@type": "Organization",
    "name": "AudioTech Industries"
  },
  "offers": {
    "@type": "Offer",
    "url": "https://example.com/products/wh-1000",
    "priceCurrency": "GBP",
    "price": "149.99",
    "priceValidUntil": "2025-12-31",
    "availability": "https://schema.org/InStock",
    "itemCondition": "https://schema.org/NewCondition",
    "seller": {
      "@type": "Organization",
      "name": "Example Electronics Ltd"
    }
  },
  "aggregateRating": {
    "@type": "AggregateRating",
    "ratingValue": "4.7",
    "reviewCount": "127",
    "bestRating": "5",
    "worstRating": "1"
  },
  "review": [
    {
      "@type": "Review",
      "author": {
        "@type": "Person",
        "name": "Sarah Johnson"
      },
      "datePublished": "2025-01-10",
      "reviewBody": "Excellent sound quality and comfortable for long listening sessions. The noise cancellation is outstanding.",
      "reviewRating": {
        "@type": "Rating",
        "ratingValue": "5",
        "bestRating": "5"
      }
    }
  ],
  "additionalProperty": [
    {
      "@type": "PropertyValue",
      "name": "Battery Life",
      "value": "40 hours"
    },
    {
      "@type": "PropertyValue",
      "name": "Weight",
      "value": "254g"
    },
    {
      "@type": "PropertyValue",
      "name": "Connectivity",
      "value": "Bluetooth 5.2, USB-C"
    },
    {
      "@type": "PropertyValue",
      "name": "Noise Cancellation",
      "value": "Active (ANC)"
    }
  ],
  "category": "Electronics > Audio > Headphones",
  "color": "Black",
  "weight": {
    "@type": "QuantitativeValue",
    "value": "254",
    "unitCode": "GRM"
  }
}
